makeroo/__init__.py
makeroo/asyncsmtp.py
makeroo/cfglib.py
makeroo/jsonlib.py
makeroo/loglib.py
makeroo/oauth2lib.py
makeroo/pkgutils.py
makeroo/static_resource_provider.py
makeroo/threadpool.py
makeroo/tornadolib.py
makeroo/gassman/__init__.py
makeroo/gassman/db.py
makeroo/gassman/i18n_utils.py
makeroo/gassman/notification_service.py
makeroo/gassman/sql.py
makeroo/gassman/templateutils.py
makeroo/gassman/tornadolib.py
makeroo/gassman/backend/__init__.py
makeroo/gassman/backend/account.py
makeroo/gassman/backend/accounts.py
makeroo/gassman/backend/admin.py
makeroo/gassman/backend/app.py
makeroo/gassman/backend/auth.py
makeroo/gassman/backend/config.py
makeroo/gassman/backend/csa.py
makeroo/gassman/backend/error_codes.py
makeroo/gassman/backend/event.py
makeroo/gassman/backend/gassman_settings.py
makeroo/gassman/backend/orders.py
makeroo/gassman/backend/people.py
makeroo/gassman/backend/person.py
makeroo/gassman/backend/rss.py
makeroo/gassman/backend/sys.py
makeroo/gassman/backend/transaction.py
makeroo/gassman/backend/transactions.py
makeroo/gassman/backend/web.py
makeroo/gassman/backend/reports_templates/delivery_date_24h_covered_body
makeroo/gassman/backend/reports_templates/delivery_date_24h_covered_subject
makeroo/gassman/backend/tornado_templates/account_update.body.email
makeroo/gassman/backend/tornado_templates/account_update.subject.email
makeroo/gassman/backend/tornado_templates/home.html
makeroo/gassman/backend/tornado_templates/joined_account.body.email
makeroo/gassman/backend/tornado_templates/joined_account.subject.email
makeroo/gassman/backend/tornado_templates/joined_google_account.body.email
makeroo/gassman/backend/tornado_templates/joined_google_account.subject.email
makeroo/gassman/backend/tornado_templates/keycloak_return.html
makeroo/gassman/backend/tornado_templates/membership_request.body.email
makeroo/gassman/backend/tornado_templates/membership_request.subject.email
makeroo/gassman/backend/tornado_templates/rss.xml
gassman-2.0.0.dist-info/LICENSE
gassman-2.0.0.dist-info/METADATA
gassman-2.0.0.dist-info/WHEEL
gassman-2.0.0.dist-info/entry_points.txt
gassman-2.0.0.dist-info/top_level.txt
gassman-2.0.0.dist-info/RECORD
