Metadata-Version: 2.1
Name: gassman
Version: 2.0.0
Summary: Web-based C.S.A. admin & management
Home-page: https://gitlab.com/makeroo/gassman
Author: Simone Pierazzini
Author-email: makeroo@gmail.com
License: MIT
Platform: any
Classifier: Development Status :: 5 - Production/Stable
Classifier: Programming Language :: Python :: 3
Classifier: Environment :: Web Environment
Classifier: License :: OSI Approved :: MIT License
Requires-Python: >=3.9
Requires-Dist: tornado (<7,>=6.1)
Requires-Dist: pymysql (<2,>=1.0.2)
Requires-Dist: xlwt (==1.3.0)
Requires-Dist: pika (<2,>=1.2.0)
Requires-Dist: cryptography (<4,>=3.4.6)
